acc_fwu/__init__.py
acc_fwu/cli.py
acc_fwu/firewall.py
acc_fwu-0.2.1.dist-info/licenses/LICENSE
acc_fwu-0.2.1.dist-info/METADATA
acc_fwu-0.2.1.dist-info/WHEEL
acc_fwu-0.2.1.dist-info/entry_points.txt
acc_fwu-0.2.1.dist-info/top_level.txt
acc_fwu-0.2.1.dist-info/RECORD
