Metadata-Version: 2.4
Name: acc-fwu
Version: 0.2.1
Summary: A tool to update Linode/ACC firewall rules with your current IP address.
Home-page: https://github.com/johnybradshaw/acc-firewall_updater
Author: John Bradshaw
Author-email: acc-fwu@bradshaw.cloud
Classifier: Programming Language :: Python :: 3
Classifier: License :: OSI Approved :: GNU General Public License v3 (GPLv3)
Classifier: Operating System :: OS Independent
Requires-Python: >=3.6
License-File: LICENSE
Requires-Dist: requests
Dynamic: author
Dynamic: author-email
Dynamic: classifier
Dynamic: description
Dynamic: description-content-type
Dynamic: home-page
Dynamic: license-file
Dynamic: requires-dist
Dynamic: requires-python
Dynamic: summary
